odoo/addons/bus_alt_connection/README.rst
odoo/addons/bus_alt_connection/__init__.py
odoo/addons/bus_alt_connection/__manifest__.py
odoo/addons/bus_alt_connection/models/__init__.py
odoo/addons/bus_alt_connection/models/bus.py
odoo/addons/bus_alt_connection/readme/CONFIGURE.md
odoo/addons/bus_alt_connection/readme/CONTRIBUTORS.md
odoo/addons/bus_alt_connection/readme/DESCRIPTION.md
odoo/addons/bus_alt_connection/readme/INSTALL.md
odoo/addons/bus_alt_connection/static/description/icon.png
odoo/addons/bus_alt_connection/static/description/index.html
odoo_addon_bus_alt_connection-19.0.1.0.0.2.dist-info/METADATA
odoo_addon_bus_alt_connection-19.0.1.0.0.2.dist-info/WHEEL
odoo_addon_bus_alt_connection-19.0.1.0.0.2.dist-info/top_level.txt
odoo_addon_bus_alt_connection-19.0.1.0.0.2.dist-info/RECORD
